djtest/__init__.py
djtest/app_inspector.py
djtest/djtest.py
djtest-0.1.9.data/scripts/djtest
djtest-0.1.9.dist-info/METADATA
djtest-0.1.9.dist-info/WHEEL
djtest-0.1.9.dist-info/top_level.txt
djtest-0.1.9.dist-info/RECORD
