Metadata-Version: 2.1
Name: djtest
Version: 0.1.9
Summary: Interactive test runner for Django projects
Home-page: https://github.com/morlandi/djtest
Author: Mario Orlandi
Author-email: morlandi@brainstorm.it
License: MIT
Keywords: django test
Platform: UNKNOWN
Classifier: Development Status :: 3 - Alpha
Classifier: License :: OSI Approved :: MIT License
Classifier: Programming Language :: Python :: 3.6
Classifier: Framework :: Django :: 2.0
Classifier: Topic :: Software Development :: Testing :: Unit
